systemd_language_server/__init__.py
systemd_language_server/assets/systemd.automount.xml
systemd_language_server/assets/systemd.exec.xml
systemd_language_server/assets/systemd.kill.xml
systemd_language_server/assets/systemd.mount.xml
systemd_language_server/assets/systemd.path.xml
systemd_language_server/assets/systemd.scope.xml
systemd_language_server/assets/systemd.service.xml
systemd_language_server/assets/systemd.socket.xml
systemd_language_server/assets/systemd.swap.xml
systemd_language_server/assets/systemd.timer.xml
systemd_language_server/assets/systemd.unit.xml
systemd_language_server/constants.py
systemd_language_server/server.py
systemd_language_server/unit.py
systemd_language_server-0.3.5.dist-info/LICENSE
systemd_language_server-0.3.5.dist-info/METADATA
systemd_language_server-0.3.5.dist-info/WHEEL
systemd_language_server-0.3.5.dist-info/entry_points.txt
systemd_language_server-0.3.5.dist-info/RECORD
